podcraft/__init__.py
podcraft/__main__.py
podcraft/cli.py
podcraft/config.py
podcraft/containers.py
podcraft/images.py
podcraft/mainobj.py
podcraft/namegen.py
podcraft/podman.py
podcraft/pods.py
podcraft/state.py
podcraft-0.1.0.dist-info/entry_points.txt
podcraft-0.1.0.dist-info/WHEEL
podcraft-0.1.0.dist-info/METADATA
podcraft-0.1.0.dist-info/RECORD
